odoo/addons/l10n_ir_hr_contract/README.rst
odoo/addons/l10n_ir_hr_contract/__init__.py
odoo/addons/l10n_ir_hr_contract/__manifest__.py
odoo/addons/l10n_ir_hr_contract/i18n/fa.po
odoo/addons/l10n_ir_hr_contract/i18n/l10n_ir_hr_contract.pot
odoo/addons/l10n_ir_hr_contract/models/__init__.py
odoo/addons/l10n_ir_hr_contract/models/hr_contract.py
odoo/addons/l10n_ir_hr_contract/models/res_config_settings.py
odoo/addons/l10n_ir_hr_contract/readme/CONFIGURE.rst
odoo/addons/l10n_ir_hr_contract/readme/CONTRIBUTORS.rst
odoo/addons/l10n_ir_hr_contract/readme/DESCRIPTION.rst
odoo/addons/l10n_ir_hr_contract/readme/USAGE.rst
odoo/addons/l10n_ir_hr_contract/static/description/icon.png
odoo/addons/l10n_ir_hr_contract/static/description/index.html
odoo/addons/l10n_ir_hr_contract/views/hr_contract_view.xml
odoo/addons/l10n_ir_hr_contract/views/res_config_settings_inherit.xml
odoo_addon_l10n_ir_hr_contract-16.0.1.0.0.3.dist-info/METADATA
odoo_addon_l10n_ir_hr_contract-16.0.1.0.0.3.dist-info/WHEEL
odoo_addon_l10n_ir_hr_contract-16.0.1.0.0.3.dist-info/top_level.txt
odoo_addon_l10n_ir_hr_contract-16.0.1.0.0.3.dist-info/RECORD
